README.md
setup.cfg
setup.py
testchecksum1/PaytmChecksum.py
testchecksum1/__init__.py
testchecksum1.egg-info/PKG-INFO
testchecksum1.egg-info/SOURCES.txt
testchecksum1.egg-info/dependency_links.txt
testchecksum1.egg-info/top_level.txt